plone.app.upgrade-3.3.1-py3.13-nspkg.pth
plone/app/upgrade/__init__.py
plone/app/upgrade/configure.zcml
plone/app/upgrade/utils.py
plone/app/upgrade/bbb_qi/InstalledProduct.py
plone/app/upgrade/bbb_qi/QuickInstallerTool.py
plone/app/upgrade/bbb_qi/__init__.py
plone/app/upgrade/bbb_qi/interfaces/__init__.py
plone/app/upgrade/bbb_qi/interfaces/installable.py
plone/app/upgrade/bbb_qi/interfaces/portal_quickinstaller.py
plone/app/upgrade/tests/__init__.py
plone/app/upgrade/tests/base.py
plone/app/upgrade/tests/test_fix_registry_settings.py
plone/app/upgrade/tests/test_upgrade.py
plone/app/upgrade/tests/test_utils.py
plone/app/upgrade/tests/skin_test/README.txt
plone/app/upgrade/tests/skin_test/sub1/README.txt
plone/app/upgrade/tests/skin_test/sub1/subsub1/README.txt
plone/app/upgrade/tests/skin_test/sub2/README.txt
plone/app/upgrade/v52/__init__.py
plone/app/upgrade/v52/alphas.py
plone/app/upgrade/v52/betas.py
plone/app/upgrade/v52/configure.zcml
plone/app/upgrade/v52/final.py
plone/app/upgrade/v52/profiles.zcml
plone/app/upgrade/v52/tests.py
plone/app/upgrade/v52/profiles/to_521/registry.xml
plone/app/upgrade/v52/profiles/to_522/registry/controlpanel.xml
plone/app/upgrade/v52/profiles/to_522/registry/image_captioning.xml
plone/app/upgrade/v52/profiles/to_alpha1/componentregistry.xml
plone/app/upgrade/v52/profiles/to_alpha1/registry.xml
plone/app/upgrade/v52/profiles/to_alpha1/skins.xml
plone/app/upgrade/v52/profiles/to_beta1/actions.xml
plone/app/upgrade/v52/profiles/to_beta1/controlpanel.xml
plone/app/upgrade/v52/profiles/to_beta1/registry.xml
plone/app/upgrade/v52/profiles/to_beta1/repositorytool.xml
plone/app/upgrade/v52/profiles/to_beta1/rolemap.xml
plone/app/upgrade/v52/profiles/to_beta1/toolset.xml
plone/app/upgrade/v52/profiles/to_rc1/registry/resources.xml
plone/app/upgrade/v52/profiles/to_rc4/registry/security.xml
plone/app/upgrade/v52/profiles/to_rc4/registry/staticresources.xml
plone/app/upgrade/v60/__init__.py
plone/app/upgrade/v60/alphas.py
plone_app_upgrade-3.3.1.dist-info/METADATA
plone_app_upgrade-3.3.1.dist-info/WHEEL
plone_app_upgrade-3.3.1.dist-info/entry_points.txt
plone_app_upgrade-3.3.1.dist-info/namespace_packages.txt
plone_app_upgrade-3.3.1.dist-info/top_level.txt
plone_app_upgrade-3.3.1.dist-info/RECORD
