Metadata-Version: 2.4
Name: plone.app.upgrade
Version: 3.3.1
Summary: Upgrade machinery for Plone.
Home-page: https://pypi.org/project/plone.app.upgrade/
Author: Plone Foundation
Author-email: plone-developers@lists.sourceforge.net
License: GPL version 2
Keywords: Plone upgrade migration
Classifier: Development Status :: 6 - Mature
Classifier: Environment :: Web Environment
Classifier: Framework :: Plone
Classifier: Framework :: Plone :: 6.0
Classifier: Framework :: Plone :: 6.1
Classifier: Framework :: Plone :: Core
Classifier: Framework :: Zope :: 5
Classifier: License :: OSI Approved :: GNU General Public License v2 (GPLv2)
Classifier: Operating System :: OS Independent
Classifier: Programming Language :: Python
Classifier: Programming Language :: Python :: 3.9
Classifier: Programming Language :: Python :: 3.10
Classifier: Programming Language :: Python :: 3.11
Classifier: Programming Language :: Python :: 3.12
Classifier: Programming Language :: Python :: 3.13
Requires-Python: >=3.9
Requires-Dist: setuptools
Requires-Dist: plone.app.caching
Requires-Dist: plone.app.redirector
Requires-Dist: plone.base
Requires-Dist: plone.behavior
Requires-Dist: plone.dexterity
Requires-Dist: plone.registry
Requires-Dist: plone.indexer
Requires-Dist: plone.folder
Requires-Dist: plone.uuid
Requires-Dist: transaction
Requires-Dist: zope.component
Requires-Dist: zope.interface
Requires-Dist: Acquisition
Requires-Dist: Products.CMFPlone>=6.0.0a1
Requires-Dist: Products.CMFCore
Requires-Dist: Products.GenericSetup
Requires-Dist: Products.PlonePAS
Requires-Dist: Products.ZCatalog
Requires-Dist: zc.relation
Requires-Dist: ZODB
Requires-Dist: Zope>=5.5
Requires-Dist: zope.intid
Provides-Extra: test
Requires-Dist: packaging; extra == "test"
Requires-Dist: plone.app.testing; extra == "test"
Requires-Dist: plone.app.redirector; extra == "test"
Requires-Dist: Products.MimetypesRegistry; extra == "test"
Dynamic: author
Dynamic: author-email
Dynamic: classifier
Dynamic: description
Dynamic: home-page
Dynamic: keywords
Dynamic: license
Dynamic: provides-extra
Dynamic: requires-dist
Dynamic: requires-python
Dynamic: summary
